ml_vite/__init__.py
ml_vite/version.py
ml_vite/feature_eng/__init__.py
ml_vite/feature_eng/base_block.py
ml_vite/feature_eng/encoding_block.py
ml_vite/imputer/__init__.py
ml_vite/imputer/gbdt_imputer.py
ml_vite/model/__init__.py
ml_vite/model/lgbm.py
ml_vite/model/nn.py
ml_vite/model/xgboost.py
ml_vite/util/__init__.py
ml_vite/util/error.py
ml_vite/util/setup.py
ml_vite/util/submission.py
ml_vite/util/timer.py
ml_vite/util/types.py
ml_vite-0.0.7.dist-info/METADATA
ml_vite-0.0.7.dist-info/WHEEL
ml_vite-0.0.7.dist-info/top_level.txt
ml_vite-0.0.7.dist-info/RECORD
