Metadata-Version: 2.1
Name: ml-vite
Version: 0.0.7
Author: kazuyan
Requires-Dist: pandas
Requires-Dist: numpy
Requires-Dist: tqdm
